{
    "metadata" : {
        "identifier": "transcendRuins:example"
    },
    "modules" : {
        "vertices": [
            [-10, 0, -10], 
            [-10, 0, 10],
            [10, 0, 10],
            [10, 0, -10],
            [-10, 20, -10],
            [-10, 20, 10],
            [10, 20, 10],
            [10, 20, -10],

            [10, 10, -10],
            [10, 10, 10],

            [10, 10, -10],
            [10, 10, 10]
        ],
        "polygons": [
            {
                "vertices": [0, 2, 1],
                "color": [255, 0, 0]
            },
            {
                "vertices": [2, 0, 3],
                "color": [255, 0, 0]
            },
            {
                "vertices": [7, 4, 5],
                "color": [0, 0, 255]
            },
            {
                "vertices": [5, 6, 7],
                "color": [0, 0, 255]
            },
            {
                "vertices": [0, 1, 5],
                "color": [255, 128, 0]
            },
            {
                "vertices": [5, 4, 0],
                "color": [255, 128, 0]
            },
            {
                "vertices": [1, 2, 6],
                "color": [255, 255, 0]
            },
            {
                "vertices": [6, 5, 1],
                "color": [255, 255, 0]
            },


            {
                "vertices": [2, 3, 8],
                "color": [0, 255, 0]
            },
            {
                "vertices": [8, 9, 2],
                "color": [0, 255, 0]
            },


            {
                "vertices": [11, 10, 7],
                "color": [0, 255, 0]
            },
            {
                "vertices": [7, 6, 11],
                "color": [0, 255, 0]
            },


            {
                "vertices": [3, 0, 4],
                "color": [0, 255, 255]
            },
            {
                "vertices": [4, 7, 3],
                "color": [0, 255, 255]
            }
        ],
        "pivotPoint": [0, 10, 0],

        "bones": {

            "armDown": {
                "pivotPoint": [10, 0, 0],
                "vertexWeights": {
                    "8": 1.0,
                    "9": 1.0
                }
            },
            "armUp": {
                "pivotPoint": [10, 20, 0],
                "vertexWeights": {
                    "10": 1.0,
                    "11": 1.0
                }
            }
        }
    }
}